{"trial_id": "2", "hyperparameters": {"space": [{"class_name": "Choice", "config": {"name": "units", "default": 64, "conditions": [], "values": [64, 128, 256], "ordered": true}}, {"class_name": "Choice", "config": {"name": "optimizer", "default": "adam", "conditions": [], "values": ["adam", "RMSProp", "SGD"], "ordered": false}}], "values": {"units": 256, "optimizer": "SGD"}}, "metrics": {"metrics": {"loss": {"direction": "min", "observations": [{"value": [0.4954630136489868], "step": 42}]}, "mean_squared_error": {"direction": "min", "observations": [{"value": [0.4954630136489868], "step": 42}]}, "val_loss": {"direction": "min", "observations": [{"value": [0.4285098612308502], "step": 42}]}, "val_mean_squared_error": {"direction": "min", "observations": [{"value": [0.4285098612308502], "step": 42}]}}}, "score": 0.4285098612308502, "best_step": 42, "status": "COMPLETED", "message": null}